odoo/addons/license/LICENSE
odoo/addons/license/README.rst
odoo/addons/license/__init__.py
odoo/addons/license/__manifest__.py
odoo/addons/license/data/ir_sequence.xml
odoo/addons/license/demo/demo.xml
odoo/addons/license/i18n/de_CH.po
odoo/addons/license/images/screen.png
odoo/addons/license/models/__init__.py
odoo/addons/license/models/license_license.py
odoo/addons/license/models/license_type.py
odoo/addons/license/models/res_partner.py
odoo/addons/license/readme/CONTRIBUTORS.md
odoo/addons/license/readme/DESCRIPTION.md
odoo/addons/license/readme/USAGE.md
odoo/addons/license/security/ir.model.access.csv
odoo/addons/license/security/security.xml
odoo/addons/license/static/description/icon.png
odoo/addons/license/static/description/index.html
odoo/addons/license/tests/TEST_INSTRUCTIONS.rst
odoo/addons/license/tests/__init__.py
odoo/addons/license/tests/test_license.py
odoo/addons/license/views/license_license.xml
odoo/addons/license/views/license_type.xml
odoo/addons/license/views/res_partner.xml
odoo_addon_license-18.0.1.0.0.dist-info/METADATA
odoo_addon_license-18.0.1.0.0.dist-info/WHEEL
odoo_addon_license-18.0.1.0.0.dist-info/top_level.txt
odoo_addon_license-18.0.1.0.0.dist-info/RECORD
